fastapi_reloader-1.3.4.dist-info/METADATA
fastapi_reloader-1.3.4.dist-info/WHEEL
fastapi_reloader-1.3.4.dist-info/entry_points.txt
fastapi_reloader/__init__.py
fastapi_reloader/core.py
fastapi_reloader/patcher.py
fastapi_reloader/runtime.js
fastapi_reloader-1.3.4.dist-info/RECORD
