Metadata-Version: 2.1
Name: fastapi-reloader
Version: 1.3.4
Project-URL: Homepage, https://github.com/promplate/hmr
Requires-Dist: asgi-lifespan~=2.0
Requires-Dist: fastapi~=0.115
